{
  "meta": {
    "source": "https://www.pracuj.pl/praca",
    "scrapedAt": "2026-03-19T10:40:50.937Z",
    "pages": 3,
    "total": 129,
    "errors": 0
  },
  "listings": [
    {
      "id": "1004717050",
      "title": "Automatyk (M/K)",
      "company": "COLIAN",
      "location": "Lublin",
      "salary": null,
      "workMode": null,
      "publishedAt": "Opublikowana: 19 marca 2026",
      "url": "https://www.pracuj.pl/praca/automatyk-m-k-lublin-gospodarcza-25,oferta,1004717050"
    },
    {
      "id": "1004717049",
      "title": "Sprzedawca / Sprzedawczyni - CALZEDONIA - ½ etatu",
      "company": "CALZ POLSKA sp. z o.o.",
      "location": "Szczecin",
      "salary": null,
      "workMode": null,
      "publishedAt": "Opublikowana: 19 marca 2026",
      "url": "https://www.pracuj.pl/praca/sprzedawca-sprzedawczyni-calzedonia-etatu-szczecin-aleja-niepodleglosci-36,oferta,1004717049"
    },
    {
      "id": "1004671456",
      "title": "Magazynier / Operator Wózka Widłowego (K/M)",
      "company": "GRUPA CE-MA SPÓŁKA Z O. O.",
      "location": "Katowice",
      "salary": null,
      "workMode": null,
      "publishedAt": "Opublikowana: 19 marca 2026",
      "url": "https://www.pracuj.pl/praca/magazynier-operator-wozka-widlowego-k-m-katowice-miedziana-15,oferta,1004671456"
    },
    {
      "id": "1004693205",
      "title": "Specjalista / Specjalistka ds. administracyjno-księgowych",
      "company": "KUBALA sp. z o.o.",
      "location": "Goleszów (pow. cieszyński)",
      "salary": null,
      "workMode": null,
      "publishedAt": "Opublikowana: 19 marca 2026",
      "url": "https://www.pracuj.pl/praca/specjalista-specjalistka-ds-administracyjno-ksiegowych-goleszow-pow-cieszynski-przemyslowa-5,oferta,1004693205"
    },
    {
      "id": "1004701561",
      "title": "SCRUM Master - branża ubezpieczeniowa",
      "company": "PEOPLE TRUST SPÓŁKA Z OGRANICZONĄ ODPOWIEDZIALNOŚCIĄ",
      "location": "Warszawa, Śródmieście",
      "salary": null,
      "workMode": null,
      "publishedAt": "Opublikowana: 19 marca 2026",
      "url": "https://www.pracuj.pl/praca/scrum-master-branza-ubezpieczeniowa-warszawa-aleja-armii-ludowej-26,oferta,1004701561"
    },
    {
      "id": "1004717046",
      "title": "3D Generalist (m/f/d)",
      "company": "Omnicom Production sp. z o.o.",
      "location": "Warszawa, Mokotów",
      "salary": null,
      "workMode": null,
      "publishedAt": "Opublikowana: 19 marca 2026",
      "url": "https://www.pracuj.pl/praca/3d-generalist-m-f-d-warszawa-wincentego-rzymowskiego-34,oferta,1004717046"
    },
    {
      "id": "1004717045",
      "title": "Doradca / Doradczyni klienta",
      "company": "Leroy Merlin Polska Sp. z o.o.",
      "location": "Łódź, Bałuty",
      "salary": null,
      "workMode": null,
      "publishedAt": "Opublikowana: 19 marca 2026",
      "url": "https://www.pracuj.pl/praca/doradca-doradczyni-klienta-lodz-pojezierska-93,oferta,1004717045"
    },
    {
      "id": "1004701558",
      "title": "Młodszy/a Inżynier/ka Procesu (Program Rozwojowy)",
      "company": "Faurecia R&D Center S.A.",
      "location": "Grójec",
      "salary": null,
      "workMode": null,
      "publishedAt": "Opublikowana: 19 marca 2026",
      "url": "https://www.pracuj.pl/praca/mlodszy-a-inzynier-ka-procesu-program-rozwojowy-grojec-spoldzielcza-4,oferta,1004701558"
    },
    {
      "id": "1004668602",
      "title": "Marketing Product Owner / Brand Manager.",
      "company": "Wyższa Szkoła Kształcenia Zawodowego",
      "location": "Wrocław, Krzyki",
      "salary": null,
      "workMode": null,
      "publishedAt": "Opublikowana: 19 marca 2026",
      "url": "https://www.pracuj.pl/praca/marketing-product-owner-brand-manager-wroclaw-plac-powstancow-slaskich-1,oferta,1004668602"
    },
    {
      "id": "1004717044",
      "title": "Lekarz Dentysta",
      "company": "Indywidualna Praktyka Stomatologiczna Wojciech Wojnowski",
      "location": "Rawicz",
      "salary": null,
      "workMode": null,
      "publishedAt": "Opublikowana: 19 marca 2026",
      "url": "https://www.pracuj.pl/praca/lekarz-dentysta-rawicz-akacjowa-22,oferta,1004717044"
    },
    {
      "id": "1004657114",
      "title": "Sprzedawca / Sprzedawczyni na stacji paliw",
      "company": "Circle K Polska Sp. z o.o.",
      "location": "Śrem",
      "salary": null,
      "workMode": null,
      "publishedAt": "Opublikowana: 19 marca 2026",
      "url": "https://www.pracuj.pl/praca/sprzedawca-sprzedawczyni-na-stacji-paliw-srem-grunwaldzka-21,oferta,1004657114"
    },
    {
      "id": "1004674030",
      "title": "Młodsza Specjalistka / Młodszy Specjalista ds. Administracji",
      "company": "PFR Nieruchomości S.A.",
      "location": "Warszawa",
      "salary": null,
      "workMode": null,
      "publishedAt": "Opublikowana: 19 marca 2026",
      "url": "https://www.pracuj.pl/praca/mlodsza-specjalistka-mlodszy-specjalista-ds-administracji-warszawa,oferta,1004674030"
    },
    {
      "id": "1004684100",
      "title": "Credit & Collections Coordinator with languages",
      "company": "TRANE POLAND sp. z o.o.",
      "location": "Warszawa, Włochy",
      "salary": null,
      "workMode": null,
      "publishedAt": "Opublikowana: 19 marca 2026",
      "url": "https://www.pracuj.pl/praca/credit-collections-coordinator-with-languages-warszawa-jutrzenki-137a,oferta,1004684100"
    },
    {
      "id": "1004683959",
      "title": "Konsultant / Konsultantka ds. zatrudnienia",
      "company": "Work Force Sp. z o.o.",
      "location": "Bydgoszcz",
      "salary": null,
      "workMode": null,
      "publishedAt": "Opublikowana: 19 marca 2026",
      "url": "https://www.pracuj.pl/praca/konsultant-konsultantka-ds-zatrudnienia-bydgoszcz,oferta,1004683959"
    },
    {
      "id": "1004683956",
      "title": "Analityk/Analityczka Sprzedaży",
      "company": "LUX MED Sp. z o.o.",
      "location": "Warszawa, Mokotów",
      "salary": null,
      "workMode": null,
      "publishedAt": "Opublikowana: 19 marca 2026",
      "url": "https://www.pracuj.pl/praca/analityk-analityczka-sprzedazy-warszawa-szturmowa-2,oferta,1004683956"
    },
    {
      "id": "1004687001",
      "title": "Programista/-ka maszyn tnących",
      "company": "Manpower",
      "location": "Konotopa (pow. warszawski zachodni)",
      "salary": null,
      "workMode": null,
      "publishedAt": "Opublikowana: 19 marca 2026",
      "url": "https://www.pracuj.pl/praca/programista-ka-maszyn-tnacych-konotopa-pow-warszawski-zachodni,oferta,1004687001"
    },
    {
      "id": "11885264",
      "title": "Blacharz Samochodowy (m/k)",
      "company": "Íslensk verkmiðlun ehf",
      "location": "Islandia",
      "salary": null,
      "workMode": null,
      "publishedAt": "Opublikowana: 19 marca 2026",
      "url": "https://www.pracuj.pl/praca/blacharz-samochodowy-m-k-islandia,oferta,11885264"
    },
    {
      "id": "11885265",
      "title": "Detailer Pojazdów Ciężarowych (k/m)",
      "company": "BAS World",
      "location": "Holandia",
      "salary": null,
      "workMode": null,
      "publishedAt": "Opublikowana: 19 marca 2026",
      "url": "https://www.pracuj.pl/praca/detailer-pojazdow-ciezarowych-k-m-holandia,oferta,11885265"
    },
    {
      "id": "1004701554",
      "title": "Manager / -ka ds. rozwoju biznesu",
      "company": "OLAVION sp. z o.o.",
      "location": "Gdańsk, Przeróbka",
      "salary": null,
      "workMode": null,
      "publishedAt": "Opublikowana: 19 marca 2026",
      "url": "https://www.pracuj.pl/praca/manager-ka-ds-rozwoju-biznesu-gdansk-siennicka-25,oferta,1004701554"
    },
    {
      "id": "1004701555",
      "title": "Security Success Engineer",
      "company": "Veeam Software",
      "location": "Miejsce pracy:Cała Polska (praca zdalna)\nSiedziba firmy:Warszawa, Śródmieście",
      "salary": null,
      "workMode": null,
      "publishedAt": "Opublikowana: 19 marca 2026",
      "url": "https://www.pracuj.pl/praca/security-success-engineer-warszawa-plac-bankowy-12,oferta,1004701555"
    },
    {
      "id": "1004717043",
      "title": "Kosmetolog (K/M/N)",
      "company": "Douglas Polska Sp. z o.o.",
      "location": "Suwałki",
      "salary": null,
      "workMode": null,
      "publishedAt": "Opublikowana: 19 marca 2026",
      "url": "https://www.pracuj.pl/praca/kosmetolog-k-m-n-suwalki-generala-jozefa-dwernickiego-15,oferta,1004717043"
    },
    {
      "id": "1004701556",
      "title": "Kierowca ciężarówki C+E",
      "company": "TDK TRANSPORT sp. z o.o.",
      "location": "Gniezno",
      "salary": null,
      "workMode": null,
      "publishedAt": "Opublikowana: 19 marca 2026",
      "url": "https://www.pracuj.pl/praca/kierowca-ciezarowki-c%2be-gniezno,oferta,1004701556"
    },
    {
      "id": "1004717042",
      "title": "Senior Financial Controller",
      "company": "HEALTH LABS CARE spółka akcyjna",
      "location": "Warszawa, Wilanów",
      "salary": null,
      "workMode": null,
      "publishedAt": "Opublikowana: 19 marca 2026",
      "url": "https://www.pracuj.pl/praca/senior-financial-controller-warszawa-franciszka-klimczaka-1,oferta,1004717042"
    },
    {
      "id": "1004671429",
      "title": "Ambasador / Ambasadorka Marki PLOOM",
      "company": "Modus",
      "location": "Luboń",
      "salary": null,
      "workMode": null,
      "publishedAt": "Opublikowana: 19 marca 2026",
      "url": "https://www.pracuj.pl/praca/ambasador-ambasadorka-marki-ploom-lubon,oferta,1004671429"
    },
    {
      "id": "1004708293",
      "title": "Starszy specjalista / Starsza specjalistka ds. kadrowo-płacowych",
      "company": "S. M. GROUP sp. z o.o.",
      "location": "Szczecin",
      "salary": null,
      "workMode": null,
      "publishedAt": "Opublikowana: 19 marca 2026",
      "url": "https://www.pracuj.pl/praca/starszy-specjalista-starsza-specjalistka-ds-kadrowo-placowych-szczecin,oferta,1004708293"
    },
    {
      "id": "1004693196",
      "title": "Kierownik regionalny / Kierowniczka regionalna - Zakład Przetwórstwa Mięsnego Matejka Joachim",
      "company": "EMMA MARKET sp. z o.o.",
      "location": "Opole",
      "salary": null,
      "workMode": null,
      "publishedAt": "Opublikowana: 19 marca 2026",
      "url": "https://www.pracuj.pl/praca/kierownik-regionalny-kierowniczka-regionalna-zaklad-przetworstwa-miesnego-matejk-opole,oferta,1004693196"
    },
    {
      "id": "1004717041",
      "title": "Pracownik fizyczny / Pracowniczka fizyczna do prac drogowych",
      "company": "RADPOL Sp. z o.o.",
      "location": "Wrocław",
      "salary": null,
      "workMode": null,
      "publishedAt": "Opublikowana: 19 marca 2026",
      "url": "https://www.pracuj.pl/praca/pracownik-fizyczny-pracowniczka-fizyczna-do-prac-drogowych-wroclaw,oferta,1004717041"
    },
    {
      "id": "11876301",
      "title": "Monter / Monterka konstrukcji stalowych (kotlarz / kotlarka)",
      "company": "PowerJobs Sp. z o.o.",
      "location": "Clermont Ferrand, Francja",
      "salary": null,
      "workMode": null,
      "publishedAt": "Opublikowana: 19 marca 2026",
      "url": "https://www.pracuj.pl/praca/monter-monterka-konstrukcji-stalowych-kotlarz-kotlarka-francja,oferta,11876301"
    },
    {
      "id": "1004686992",
      "title": "Koordynator/Koordynatorka Projektu",
      "company": "MANDORIA SPÓŁKA Z OGRANICZONĄ ODPOWIEDZIALNOŚCIĄ",
      "location": "Rzgów",
      "salary": null,
      "workMode": null,
      "publishedAt": "Opublikowana: 19 marca 2026",
      "url": "https://www.pracuj.pl/praca/koordynator-koordynatorka-projektu-rzgow-miasto-mody-2,oferta,1004686992"
    },
    {
      "id": "1004687000",
      "title": "Project Manager",
      "company": "MANDORIA SPÓŁKA Z OGRANICZONĄ ODPOWIEDZIALNOŚCIĄ",
      "location": "Rzgów",
      "salary": null,
      "workMode": null,
      "publishedAt": "Opublikowana: 19 marca 2026",
      "url": "https://www.pracuj.pl/praca/project-manager-rzgow-miasto-mody-2,oferta,1004687000"
    },
    {
      "id": "1004693191",
      "title": "Zgrzewacz rur (k/m)",
      "company": "EL PROFESSIONAL SPÓŁKA Z OGRANICZONĄ ODPOWIEDZIALNOŚCIĄ",
      "location": "Kębłowo (pow. wejherowski)",
      "salary": null,
      "workMode": null,
      "publishedAt": "Opublikowana: 19 marca 2026",
      "url": "https://www.pracuj.pl/praca/zgrzewacz-rur-k-m-keblowo-pow-wejherowski,oferta,1004693191"
    },
    {
      "id": "1004693189",
      "title": "Customer Communication and Sales Support Specialist with Kazakh",
      "company": "Concentrix CVG International Sp. z o.o.",
      "location": "Katowice",
      "salary": null,
      "workMode": null,
      "publishedAt": "Opublikowana: 19 marca 2026",
      "url": "https://www.pracuj.pl/praca/customer-communication-and-sales-support-specialist-with-kazakh-katowice-zabrska-19,oferta,1004693189"
    },
    {
      "id": "1004717040",
      "title": "Technolog - Programista maszyn CNC",
      "company": "ARTDAM SPÓŁKA Z OGRANICZONĄ ODPOWIEDZIALNOŚCIĄ",
      "location": "Stanowice (pow. oławski)",
      "salary": null,
      "workMode": null,
      "publishedAt": "Opublikowana: 19 marca 2026",
      "url": "https://www.pracuj.pl/praca/technolog-programista-maszyn-cnc-stanowice-pow-olawski,oferta,1004717040"
    },
    {
      "id": "1004693193",
      "title": "Doradca / Doradczyni klienta - Kasjer / Kasjerka",
      "company": "KRAFT W ŁÓDZKIM sp. z o.o.",
      "location": "Łódź, Bałuty",
      "salary": null,
      "workMode": null,
      "publishedAt": "Opublikowana: 19 marca 2026",
      "url": "https://www.pracuj.pl/praca/doradca-doradczyni-klienta-kasjer-kasjerka-lodz-stefana-3a,oferta,1004693193"
    },
    {
      "id": "1004717039",
      "title": "Monter instalacji technologicznych",
      "company": "Technologie i Techniki Procesowe 3 AQUA Sp. z o.o.",
      "location": "Marki",
      "salary": null,
      "workMode": null,
      "publishedAt": "Opublikowana: 19 marca 2026",
      "url": "https://www.pracuj.pl/praca/monter-instalacji-technologicznych-marki,oferta,1004717039"
    },
    {
      "id": "1004717038",
      "title": "Inżynier budowy",
      "company": "Przedsiębiorstwo Budowlane „Latusek” GJ Invest Sp. z o.o. Sp.k",
      "location": "Katowice",
      "salary": null,
      "workMode": null,
      "publishedAt": "Opublikowana: 19 marca 2026",
      "url": "https://www.pracuj.pl/praca/inzynier-budowy-katowice-ceglana-50,oferta,1004717038"
    },
    {
      "id": "1004683953",
      "title": "Doradca / Doradczyni klienta w sklepie",
      "company": "JOTT",
      "location": "Gdynia, Orłowo",
      "salary": null,
      "workMode": null,
      "publishedAt": "Opublikowana: 19 marca 2026",
      "url": "https://www.pracuj.pl/praca/doradca-doradczyni-klienta-w-sklepie-gdynia-aleja-zwyciestwa-256,oferta,1004683953"
    },
    {
      "id": "1004683954",
      "title": "Specjalista / Specjalistka ds. eCommerce",
      "company": "EUROCERAMIKA MATERIAŁY BUDOWLANE sp. z o.o.",
      "location": "Warszawa",
      "salary": null,
      "workMode": null,
      "publishedAt": "Opublikowana: 19 marca 2026",
      "url": "https://www.pracuj.pl/praca/specjalista-specjalistka-ds-ecommerce-warszawa,oferta,1004683954"
    },
    {
      "id": "1004683948",
      "title": "Inżynier budowy fit-out",
      "company": "MUNIAK sp. z o.o. SPÓŁKA KOMANDYTOWA",
      "location": "Warszawa, Bemowo",
      "salary": null,
      "workMode": null,
      "publishedAt": "Opublikowana: 19 marca 2026",
      "url": "https://www.pracuj.pl/praca/inzynier-budowy-fit-out-warszawa-dywizjonu-303-139,oferta,1004683948"
    },
    {
      "id": "1004717037",
      "title": "Asystent ds. rachunkowości (k/m)",
      "company": "Business Support Solution Spółka Akcyjna (BSS)",
      "location": "Łódź, Bałuty",
      "salary": null,
      "workMode": null,
      "publishedAt": "Opublikowana: 19 marca 2026",
      "url": "https://www.pracuj.pl/praca/asystent-ds-rachunkowosci-k-m-lodz-pojezierska-90a,oferta,1004717037"
    },
    {
      "id": "1004683946",
      "title": "Konstruktor / Konstruktorka",
      "company": "ENGINOVA SP. Z O.O.",
      "location": "Kutno",
      "salary": null,
      "workMode": null,
      "publishedAt": "Opublikowana: 19 marca 2026",
      "url": "https://www.pracuj.pl/praca/konstruktor-konstruktorka-kutno-wschodnia-11,oferta,1004683946"
    },
    {
      "id": "1004674020",
      "title": "Pracownik / Pracowniczka drukarni",
      "company": "Market Print Global Sp. z o.o.",
      "location": "Warszawa, Bemowo",
      "salary": null,
      "workMode": null,
      "publishedAt": "Opublikowana: 19 marca 2026",
      "url": "https://www.pracuj.pl/praca/pracownik-pracowniczka-drukarni-warszawa-fortuny-3a,oferta,1004674020"
    },
    {
      "id": "1004717036",
      "title": "Pracownik Ochrony /Obiekt Handlowy ,Trzebiatów k/m",
      "company": "Solid Security Sp. z o.o.",
      "location": "Trzebiatów",
      "salary": null,
      "workMode": null,
      "publishedAt": "Opublikowana: 19 marca 2026",
      "url": "https://www.pracuj.pl/praca/pracownik-ochrony-obiekt-handlowy-trzebiatow-k-m-trzebiatow,oferta,1004717036"
    },
    {
      "id": "1004717035",
      "title": "T Hub Internship - IT DevOps Section",
      "company": "T-Mobile",
      "location": "Warszawa, Mokotów",
      "salary": null,
      "workMode": null,
      "publishedAt": "Opublikowana: 19 marca 2026",
      "url": "https://www.pracuj.pl/praca/t-hub-internship-it-devops-section-warszawa-marynarska-12,oferta,1004717035"
    },
    {
      "id": "1004717034",
      "title": "Regionalny przedstawiciel handlowy",
      "company": "LASIT LASER POLSKA sp. z o.o.",
      "location": "Miejsce pracy:Cała Polska (praca zdalna)\nSiedziba firmy:Łódź",
      "salary": null,
      "workMode": null,
      "publishedAt": "Opublikowana: 19 marca 2026",
      "url": "https://www.pracuj.pl/praca/regionalny-przedstawiciel-handlowy-lodz,oferta,1004717034"
    },
    {
      "id": "1004701541",
      "title": "Młodszy Przedstawiciel Handlowy / Młodsza Przedstawicielka Handlowa",
      "company": "ILLUSTRO Doradztwo S.C.",
      "location": "Kluczbork",
      "salary": null,
      "workMode": null,
      "publishedAt": "Opublikowana: 19 marca 2026",
      "url": "https://www.pracuj.pl/praca/mlodszy-przedstawiciel-handlowy-mlodsza-przedstawicielka-handlowa-kluczbork,oferta,1004701541"
    },
    {
      "id": "1004701540",
      "title": "Kierownik/czka ds. zakupów operacyjnych",
      "company": "Grafton Recruitment",
      "location": "Oborniki",
      "salary": null,
      "workMode": null,
      "publishedAt": "Opublikowana: 19 marca 2026",
      "url": "https://www.pracuj.pl/praca/kierownik-czka-ds-zakupow-operacyjnych-oborniki,oferta,1004701540"
    },
    {
      "id": "1004704308",
      "title": "Terapeuta Integracji Sensorycznej (k/m)",
      "company": "SOS Wioski Dziecięce w Polsce",
      "location": "Warszawa",
      "salary": null,
      "workMode": null,
      "publishedAt": "Opublikowana: 19 marca 2026",
      "url": "https://www.pracuj.pl/praca/terapeuta-integracji-sensorycznej-k-m-warszawa,oferta,1004704308"
    },
    {
      "id": "1004674012",
      "title": "Analityk / Analityczka ds. rozwoju nieruchomości mieszkaniowych",
      "company": "Ronson Development Management Sp. z o.o.",
      "location": "Warszawa, Ursynów",
      "salary": null,
      "workMode": null,
      "publishedAt": "Opublikowana: 19 marca 2026",
      "url": "https://www.pracuj.pl/praca/analityk-analityczka-ds-rozwoju-nieruchomosci-mieszkaniowych-warszawa-aleja-komisji-edukacji-narodowej-57,oferta,1004674012"
    },
    {
      "id": "1004707988",
      "title": "Operator sterowni (produkcja) (m/k/n)",
      "company": "Kopalnie Dolomitu S.A.",
      "location": "Wojnowice (pow. opatowski)",
      "salary": null,
      "workMode": null,
      "publishedAt": "Opublikowana: 19 marca 2026",
      "url": "https://www.pracuj.pl/praca/operator-sterowni-produkcja-m-k-n-wojnowice-pow-opatowski,oferta,1004707988"
    },
    {
      "id": "1004717032",
      "title": "Konserwator/ka - Operator/ka Maszyn i Urządzeń",
      "company": "POZBRUK",
      "location": "Janikowo (pow. poznański)",
      "salary": null,
      "workMode": null,
      "publishedAt": "Opublikowana: 19 marca 2026",
      "url": "https://www.pracuj.pl/praca/konserwator-ka-operator-ka-maszyn-i-urzadzen-janikowo-pow-poznanski,oferta,1004717032"
    },
    {
      "id": "1004683943",
      "title": "Software Engineer (DevOps) - Site Reliability",
      "company": "Revolut Ltd",
      "location": "Miejsce pracy:Cała Polska (praca zdalna)\nSiedziba firmy:Kraków",
      "salary": null,
      "workMode": null,
      "publishedAt": "Opublikowana: 19 marca 2026",
      "url": "https://www.pracuj.pl/praca/software-engineer-devops-site-reliability-krakow,oferta,1004683943"
    },
    {
      "id": "1004717031",
      "title": "Kierownik Restauracji | Zakopiańska (m/k/d)",
      "company": "Max Poland Sp. z o.o.",
      "location": "Kraków, Łagiewniki-Borek Fałęcki",
      "salary": null,
      "workMode": null,
      "publishedAt": "Opublikowana: 19 marca 2026",
      "url": "https://www.pracuj.pl/praca/kierownik-restauracji-zakopianska-m-k-d-krakow-zakopianska-70b,oferta,1004717031"
    },
    {
      "id": "1004683942",
      "title": "Asystent / Asystentka zarządu",
      "company": "AMC AVIATION sp. z o.o.",
      "location": "Nowy Dwór Mazowiecki",
      "salary": null,
      "workMode": null,
      "publishedAt": "Opublikowana: 19 marca 2026",
      "url": "https://www.pracuj.pl/praca/asystent-asystentka-zarzadu-nowy-dwor-mazowiecki,oferta,1004683942"
    },
    {
      "id": "1004717030",
      "title": "Ratownik",
      "company": "Hotel InterContinental Warszawa",
      "location": "Warszawa, Śródmieście",
      "salary": null,
      "workMode": null,
      "publishedAt": "Opublikowana: 19 marca 2026",
      "url": "https://www.pracuj.pl/praca/ratownik-warszawa-emilii-plater-49,oferta,1004717030"
    },
    {
      "id": "1004717029",
      "title": "Operator / Operatorka maszyny do oprawy zeszytowej",
      "company": "KRM DRUK MILLER SPÓŁKA KOMANDYTOWA",
      "location": "Warszawa, Targówek",
      "salary": null,
      "workMode": null,
      "publishedAt": "Opublikowana: 19 marca 2026",
      "url": "https://www.pracuj.pl/praca/operator-operatorka-maszyny-do-oprawy-zeszytowej-warszawa-matuszewska-14,oferta,1004717029"
    },
    {
      "id": "1004707982",
      "title": "Kierownik Salonu (m/k)",
      "company": "TATUUM",
      "location": "Tychy",
      "salary": null,
      "workMode": null,
      "publishedAt": "Opublikowana: 19 marca 2026",
      "url": "https://www.pracuj.pl/praca/kierownik-salonu-m-k-tychy,oferta,1004707982"
    },
    {
      "id": "1004666138",
      "title": "Backend Developer (NestJS)",
      "company": "CodeTalent Sp. z o.o.",
      "location": "Miejsce pracy:Cała Polska (praca zdalna)\nSiedziba firmy:Warszawa, Wola",
      "salary": null,
      "workMode": null,
      "publishedAt": "Opublikowana: 19 marca 2026",
      "url": "https://www.pracuj.pl/praca/backend-developer-nestjs-warszawa-marcina-kasprzaka-31,oferta,1004666138"
    },
    {
      "id": "1004717028",
      "title": "Specjalista / Specjalistka ds. kadr i płac",
      "company": "Elżbieta Andryszewska Consulting",
      "location": "Raszyn (pow. pruszkowski)",
      "salary": null,
      "workMode": null,
      "publishedAt": "Opublikowana: 19 marca 2026",
      "url": "https://www.pracuj.pl/praca/specjalista-specjalistka-ds-kadr-i-plac-raszyn-pow-pruszkowski,oferta,1004717028"
    },
    {
      "id": "1004680858",
      "title": "Specjalista / Specjalistka ds. sprzedaży w salonie Orange",
      "company": "GTI Sp. z o.o.",
      "location": "Gliwice",
      "salary": null,
      "workMode": null,
      "publishedAt": "Opublikowana: 19 marca 2026",
      "url": "https://www.pracuj.pl/praca/specjalista-specjalistka-ds-sprzedazy-w-salonie-orange-gliwice-aleja-jana-nowaka-jezioranskiego-1,oferta,1004680858"
    },
    {
      "id": "1004698791",
      "title": "Specjalista ds. obsługi klienta (k/m/n)",
      "company": "Hellmann Worldwide Logistics Polska sp. z o.o. sp.k",
      "location": "Tyniec Mały (pow. wrocławski)",
      "salary": null,
      "workMode": null,
      "publishedAt": "Opublikowana: 19 marca 2026",
      "url": "https://www.pracuj.pl/praca/specjalista-ds-obslugi-klienta-k-m-n-tyniec-maly-pow-wroclawski-ryszarda-chomicza-26,oferta,1004698791"
    },
    {
      "id": "1004704277",
      "title": "Pracownik produkcji – montaż",
      "company": "Manpower",
      "location": "Tychy",
      "salary": null,
      "workMode": null,
      "publishedAt": "Opublikowana: 19 marca 2026",
      "url": "https://www.pracuj.pl/praca/pracownik-produkcji-montaz-tychy,oferta,1004704277"
    },
    {
      "id": "1004683940",
      "title": "Senior Software Engineer (Devops) - Developer Experience",
      "company": "Revolut Ltd",
      "location": "Miejsce pracy:Cała Polska (praca zdalna)\nSiedziba firmy:Kraków",
      "salary": null,
      "workMode": null,
      "publishedAt": "Opublikowana: 19 marca 2026",
      "url": "https://www.pracuj.pl/praca/senior-software-engineer-devops-developer-experience-krakow,oferta,1004683940"
    },
    {
      "id": "1004717026",
      "title": "Kierowca C+E",
      "company": "PRZEDSIĘBIORSTWO HANDLOWO USŁUGOWE \"HAMER\" s.c.",
      "location": "Prochowice",
      "salary": null,
      "workMode": null,
      "publishedAt": "Opublikowana: 19 marca 2026",
      "url": "https://www.pracuj.pl/praca/kierowca-c%2be-prochowice,oferta,1004717026"
    },
    {
      "id": "1004683939",
      "title": "Kasjer - Sprzedawca (m/k)",
      "company": "Intermarché",
      "location": "Radlin",
      "salary": null,
      "workMode": null,
      "publishedAt": "Opublikowana: 19 marca 2026",
      "url": "https://www.pracuj.pl/praca/kasjer-sprzedawca-m-k-radlin-mariacka-38,oferta,1004683939"
    },
    {
      "id": "1004717025",
      "title": "Specjalista ds. handlu zagranicznego (k/m)",
      "company": "WB Electronics S.A.",
      "location": "Warszawa",
      "salary": null,
      "workMode": null,
      "publishedAt": "Opublikowana: 19 marca 2026",
      "url": "https://www.pracuj.pl/praca/specjalista-ds-handlu-zagranicznego-k-m-warszawa,oferta,1004717025"
    },
    {
      "id": "1004683932",
      "title": "Kucharz / Kucharka",
      "company": "BISTRO MAŁY GARNUSZEK sp. z o.o.",
      "location": "Bydgoszcz",
      "salary": null,
      "workMode": null,
      "publishedAt": "Opublikowana: 19 marca 2026",
      "url": "https://www.pracuj.pl/praca/kucharz-kucharka-bydgoszcz-unii-lubelskiej-4c,oferta,1004683932"
    },
    {
      "id": "1004693155",
      "title": "Specjalista / Specjalistka ds. wdrożeń i serwisu oprogramowania",
      "company": "ELEWATORSOFT.PL sp. z o.o.",
      "location": "Piła",
      "salary": null,
      "workMode": null,
      "publishedAt": "Opublikowana: 19 marca 2026",
      "url": "https://www.pracuj.pl/praca/specjalista-specjalistka-ds-wdrozen-i-serwisu-oprogramowania-pila-wladyslawa-sikorskiego-33,oferta,1004693155"
    },
    {
      "id": "1004693154",
      "title": "Rekruter / Rekruterka",
      "company": "ZG CARE SPÓŁKA Z OGRANICZONĄ ODPOWIEDZIALNOŚCIĄ",
      "location": "Zielona Góra",
      "salary": null,
      "workMode": null,
      "publishedAt": "Opublikowana: 19 marca 2026",
      "url": "https://www.pracuj.pl/praca/rekruter-rekruterka-zielona-gora-koscielna-2,oferta,1004693154"
    },
    {
      "id": "1004683926",
      "title": "Doradca Klienta (k/m)",
      "company": "Neonet S.A.",
      "location": "Słupca",
      "salary": null,
      "workMode": null,
      "publishedAt": "Opublikowana: 19 marca 2026",
      "url": "https://www.pracuj.pl/praca/doradca-klienta-k-m-slupca,oferta,1004683926"
    },
    {
      "id": "1004683925",
      "title": "Doradca Klienta (k/m)",
      "company": "Neonet S.A.",
      "location": "Pisz",
      "salary": null,
      "workMode": null,
      "publishedAt": "Opublikowana: 19 marca 2026",
      "url": "https://www.pracuj.pl/praca/doradca-klienta-k-m-pisz,oferta,1004683925"
    },
    {
      "id": "1004683930",
      "title": "Doradca Klienta (k/m)",
      "company": "Neonet S.A.",
      "location": "Zielona Góra",
      "salary": null,
      "workMode": null,
      "publishedAt": "Opublikowana: 19 marca 2026",
      "url": "https://www.pracuj.pl/praca/doradca-klienta-k-m-zielona-gora,oferta,1004683930"
    },
    {
      "id": "1004686977",
      "title": "Specjalista / Specjalistka ds. Obsługi Klienta Technicznego",
      "company": "Marat Sp. z o.o.",
      "location": "Jarocin (pow. jarociński)",
      "salary": null,
      "workMode": null,
      "publishedAt": "Opublikowana: 19 marca 2026",
      "url": "https://www.pracuj.pl/praca/specjalista-specjalistka-ds-obslugi-klienta-technicznego-jarocin-pow-jarocinski,oferta,1004686977"
    },
    {
      "id": "1004686975",
      "title": "Księgowa (m/f/d)",
      "company": "Gulermak S.A.",
      "location": "Warszawa, Wola",
      "salary": null,
      "workMode": null,
      "publishedAt": "Opublikowana: 19 marca 2026",
      "url": "https://www.pracuj.pl/praca/ksiegowa-m-f-d-warszawa-gieldowa-7,oferta,1004686975"
    },
    {
      "id": "1004686978",
      "title": "Kupiec (Specjalista / Specjalistka) w Zespole Zakupów",
      "company": "EcoWipes",
      "location": "Nowy Modlin (pow. nowodworski)",
      "salary": null,
      "workMode": null,
      "publishedAt": "Opublikowana: 19 marca 2026",
      "url": "https://www.pracuj.pl/praca/kupiec-specjalista-specjalistka-w-zespole-zakupow-nowy-modlin-pow-nowodworski,oferta,1004686978"
    },
    {
      "id": "1004701536",
      "title": "Specjalista / specjalistka ds. księgowości z angielskim",
      "company": "Grafton Recruitment",
      "location": "Łomianki",
      "salary": null,
      "workMode": null,
      "publishedAt": "Opublikowana: 19 marca 2026",
      "url": "https://www.pracuj.pl/praca/specjalista-specjalistka-ds-ksiegowosci-z-angielskim-lomianki,oferta,1004701536"
    },
    {
      "id": "1004701532",
      "title": "Stanowisko ds. rozwoju ERTMS (k/m)",
      "company": "PKP Polskie Linie Kolejowe S.A",
      "location": "Warszawa",
      "salary": null,
      "workMode": null,
      "publishedAt": "Opublikowana: 19 marca 2026",
      "url": "https://www.pracuj.pl/praca/stanowisko-ds-rozwoju-ertms-k-m-warszawa,oferta,1004701532"
    },
    {
      "id": "1004711439",
      "title": "Pracownik kompletowania zamówień (k/m) - magazyn odzieży i artykułów domowych",
      "company": "Gi Group Poland S.A.",
      "location": "Skierniewice",
      "salary": null,
      "workMode": null,
      "publishedAt": "Opublikowana: 19 marca 2026",
      "url": "https://www.pracuj.pl/praca/pracownik-kompletowania-zamowien-k-m-magazyn-odziezy-i-artykulow-domowych-skierniewice,oferta,1004711439"
    },
    {
      "id": "1004683929",
      "title": "Sprzedawca / Sprzedawczyni działu tradycyjnego",
      "company": "Intermarché",
      "location": "Radlin",
      "salary": null,
      "workMode": null,
      "publishedAt": "Opublikowana: 19 marca 2026",
      "url": "https://www.pracuj.pl/praca/sprzedawca-sprzedawczyni-dzialu-tradycyjnego-radlin-mariacka-38,oferta,1004683929"
    },
    {
      "id": "1004683927",
      "title": "Osoba do sprzątania powierzchni magazynu",
      "company": "AMLUX Sp. z o.o.",
      "location": "Mszczonów",
      "salary": null,
      "workMode": null,
      "publishedAt": "Opublikowana: 19 marca 2026",
      "url": "https://www.pracuj.pl/praca/osoba-do-sprzatania-powierzchni-magazynu-mszczonow,oferta,1004683927"
    },
    {
      "id": "1004717021",
      "title": "Senior Transfer Agency Shareholder Services Representative",
      "company": "Brown Brothers Harriman",
      "location": "Kraków, Podgórze",
      "salary": null,
      "workMode": null,
      "publishedAt": "Opublikowana: 19 marca 2026",
      "url": "https://www.pracuj.pl/praca/senior-transfer-agency-shareholder-services-representative-krakow-stanislawa-klimeckiego-1,oferta,1004717021"
    },
    {
      "id": "1004717020",
      "title": "Radca prawny / Radczyni prawna / Aplikant(ka) w Dziale Prawa Cywilnego",
      "company": "ZIEMSKI&PARTNERS KANCELARIA PRAWNA KOSTRZEWSKA, KOŁODZIEJCZAK I WSPÓLNICY SPÓŁKA KOMANDYTOWA",
      "location": "Poznań, Grunwald",
      "salary": null,
      "workMode": null,
      "publishedAt": "Opublikowana: 19 marca 2026",
      "url": "https://www.pracuj.pl/praca/radca-prawny-radczyni-prawna-aplikant-ka-w-dziale-prawa-cywilnego-poznan-ulica-jozefa-strusia-10,oferta,1004717020"
    },
    {
      "id": "1004717019",
      "title": "Starszy Specjalista / Starsza Specjalistka w Dziale Strategii i Rozwoju",
      "company": "Muzeum Historyczne Miasta Krakowa",
      "location": "Kraków, Stare Miasto",
      "salary": null,
      "workMode": null,
      "publishedAt": "Opublikowana: 19 marca 2026",
      "url": "https://www.pracuj.pl/praca/starszy-specjalista-starsza-specjalistka-w-dziale-strategii-i-rozwoju-krakow-rynek-glowny-35,oferta,1004717019"
    },
    {
      "id": "1004701530",
      "title": "Przedstawiciel handlowy / Przedstawicielka handlowa",
      "company": "MARS - TDLM SP. Z O.O. SPÓŁKA KOMANDYTOWA",
      "location": "Częstochowa",
      "salary": null,
      "workMode": null,
      "publishedAt": "Opublikowana: 19 marca 2026",
      "url": "https://www.pracuj.pl/praca/przedstawiciel-handlowy-przedstawicielka-handlowa-czestochowa,oferta,1004701530"
    },
    {
      "id": "1004683924",
      "title": "Kierownik zmianowy",
      "company": "Intermarché",
      "location": "Radlin",
      "salary": null,
      "workMode": null,
      "publishedAt": "Opublikowana: 19 marca 2026",
      "url": "https://www.pracuj.pl/praca/kierownik-zmianowy-radlin-mariacka-38,oferta,1004683924"
    },
    {
      "id": "1004683922",
      "title": "Doradca Klienta / Doradczyni Klienta",
      "company": "PRO PEOPLE Spółka z ograniczoną odpowiedzialnością",
      "location": "Warszawa, Wola",
      "salary": null,
      "workMode": null,
      "publishedAt": "Opublikowana: 19 marca 2026",
      "url": "https://www.pracuj.pl/praca/doradca-klienta-doradczyni-klienta-warszawa-gorczewska-124,oferta,1004683922"
    },
    {
      "id": "1004683920",
      "title": "Kierownik Regionu / Kierowniczka Regionu HVAC",
      "company": "Ventia Sp. z o.o.",
      "location": "Bydgoszcz",
      "salary": null,
      "workMode": null,
      "publishedAt": "Opublikowana: 19 marca 2026",
      "url": "https://www.pracuj.pl/praca/kierownik-regionu-kierowniczka-regionu-hvac-bydgoszcz,oferta,1004683920"
    },
    {
      "id": "1004683919",
      "title": "Doradca Klienta / Doradczyni Klienta",
      "company": "PRO PEOPLE Spółka z ograniczoną odpowiedzialnością",
      "location": "Warszawa, Targówek",
      "salary": null,
      "workMode": null,
      "publishedAt": "Opublikowana: 19 marca 2026",
      "url": "https://www.pracuj.pl/praca/doradca-klienta-doradczyni-klienta-warszawa-malborska-35,oferta,1004683919"
    },
    {
      "id": "1004663338",
      "title": "Elektryk (k/m/n)",
      "company": "FAM SPÓŁKA AKCYJNA",
      "location": "Opole",
      "salary": null,
      "workMode": null,
      "publishedAt": "Opublikowana: 19 marca 2026",
      "url": "https://www.pracuj.pl/praca/elektryk-k-m-n-opole-odrzanska-20,oferta,1004663338"
    },
    {
      "id": "1004717018",
      "title": "Technik / Techniczka Utrzymania Obiektu",
      "company": "AGENCJA ZATRUDNIENIA KS SERVICE S.A.",
      "location": "Gryfice",
      "salary": null,
      "workMode": null,
      "publishedAt": "Opublikowana: 19 marca 2026",
      "url": "https://www.pracuj.pl/praca/technik-techniczka-utrzymania-obiektu-gryfice,oferta,1004717018"
    },
    {
      "id": "1004686972",
      "title": "Sales and Technical Dealer Support for SINUMERIK and Machine Tool Systems (Vertical Indirect Sales Professional) (f/m/d)",
      "company": "Siemens Sp. z o.o",
      "location": "Warszawa",
      "salary": null,
      "workMode": null,
      "publishedAt": "Opublikowana: 19 marca 2026",
      "url": "https://www.pracuj.pl/praca/sales-and-technical-dealer-support-for-sinumerik-and-machine-tool-systems-vertic-warszawa,oferta,1004686972"
    },
    {
      "id": "1004686967",
      "title": "Recepcjonista / Recepcjonistka do hotelu",
      "company": "Olimpus Investment Sp. z o.o.",
      "location": "Łódź",
      "salary": null,
      "workMode": null,
      "publishedAt": "Opublikowana: 19 marca 2026",
      "url": "https://www.pracuj.pl/praca/recepcjonista-recepcjonistka-do-hotelu-lodz,oferta,1004686967"
    },
    {
      "id": "1004686971",
      "title": "Channel Development Manager (Portfolio & Pricing)",
      "company": "Newell Poland Services Sp. z o.o.",
      "location": "Poznań, Stare Miasto",
      "salary": null,
      "workMode": null,
      "publishedAt": "Opublikowana: 19 marca 2026",
      "url": "https://www.pracuj.pl/praca/channel-development-manager-portfolio-pricing-poznan-plac-wladyslawa-andersa-7,oferta,1004686971"
    },
    {
      "id": "1004693150",
      "title": "Specjalista ds. Doradztwa i Usług Odpadowych (M/K)",
      "company": "PreZero Polska Sp. z o.o.",
      "location": "Piotrowo Pierwsze (pow. kościański)",
      "salary": null,
      "workMode": null,
      "publishedAt": "Opublikowana: 19 marca 2026",
      "url": "https://www.pracuj.pl/praca/specjalista-ds-doradztwa-i-uslug-odpadowych-m-k-piotrowo-pierwsze-pow-koscianski,oferta,1004693150"
    },
    {
      "id": "1004701525",
      "title": "Software Developer",
      "company": "Meshnex B.V.",
      "location": "Chojnice",
      "salary": null,
      "workMode": null,
      "publishedAt": "Opublikowana: 19 marca 2026",
      "url": "https://www.pracuj.pl/praca/software-developer-chojnice,oferta,1004701525"
    },
    {
      "id": "1004701526",
      "title": "Specjalista/ka ds. prawa zamówień publicznych",
      "company": "HR Progress Sp. z o.o.",
      "location": "Miejsce pracy:Cała Polska (praca zdalna)\nSiedziba firmy:Lubin",
      "salary": null,
      "workMode": null,
      "publishedAt": "Opublikowana: 19 marca 2026",
      "url": "https://www.pracuj.pl/praca/specjalista-ka-ds-prawa-zamowien-publicznych-lubin,oferta,1004701526"
    },
    {
      "id": "1004701527",
      "title": "Sales Manager GEELY (Retail)",
      "company": "Jameel Motors Poland Sp. z o.o",
      "location": "Warszawa",
      "salary": null,
      "workMode": null,
      "publishedAt": "Opublikowana: 19 marca 2026",
      "url": "https://www.pracuj.pl/praca/sales-manager-geely-retail-warszawa,oferta,1004701527"
    },
    {
      "id": "1004704268",
      "title": "Przedstawiciel handlowy / Przedstawicielka handlowa",
      "company": "HireWise Szymon Negacz sp.k.",
      "location": "Katowice",
      "salary": null,
      "workMode": null,
      "publishedAt": "Opublikowana: 19 marca 2026",
      "url": "https://www.pracuj.pl/praca/przedstawiciel-handlowy-przedstawicielka-handlowa-katowice,oferta,1004704268"
    },
    {
      "id": "1004704258",
      "title": "Kierowca kat. B – sprzedaż cateringu (K/M)",
      "company": "Sandwicz Szop",
      "location": "Bydgoszcz",
      "salary": null,
      "workMode": null,
      "publishedAt": "Opublikowana: 19 marca 2026",
      "url": "https://www.pracuj.pl/praca/kierowca-kat-b-sprzedaz-cateringu-k-m-bydgoszcz,oferta,1004704258"
    },
    {
      "id": "1004683918",
      "title": "Administrator biura ze znajomością jęz. angielskiego",
      "company": "WESTERN GLOBAL POLAND sp. z o.o.",
      "location": "Łódź",
      "salary": null,
      "workMode": null,
      "publishedAt": "Opublikowana: 19 marca 2026",
      "url": "https://www.pracuj.pl/praca/administrator-biura-ze-znajomoscia-jez-angielskiego-lodz,oferta,1004683918"
    },
    {
      "id": "1004683891",
      "title": "Kierownik / Kierowniczka budowy",
      "company": "PRZEDSIĘBIORSTWO ORGANIZACJI BUDOWNICTWA POBUD SP Z O O",
      "location": "Bydgoszcz",
      "salary": null,
      "workMode": null,
      "publishedAt": "Opublikowana: 19 marca 2026",
      "url": "https://www.pracuj.pl/praca/kierownik-kierowniczka-budowy-bydgoszcz-glinki-146,oferta,1004683891"
    },
    {
      "id": "1004683888",
      "title": "Listonosz / Listonoszka",
      "company": "Poczta Polska Spółka Akcyjna",
      "location": "Zgierz",
      "salary": null,
      "workMode": null,
      "publishedAt": "Opublikowana: 19 marca 2026",
      "url": "https://www.pracuj.pl/praca/listonosz-listonoszka-zgierz,oferta,1004683888"
    },
    {
      "id": "1004683884",
      "title": "Elektromonter / Elektromonterka",
      "company": "PRZEDSIĘBIORSTWO ORGANIZACJI BUDOWNICTWA POBUD SP Z O O",
      "location": "Bydgoszcz",
      "salary": null,
      "workMode": null,
      "publishedAt": "Opublikowana: 19 marca 2026",
      "url": "https://www.pracuj.pl/praca/elektromonter-elektromonterka-bydgoszcz-glinki-146,oferta,1004683884"
    },
    {
      "id": "1004717016",
      "title": "Operator/ka montażu - ślusarz",
      "company": "MASTEC WTECH SP. Z O.O.",
      "location": "Wyry (pow. mikołowski)",
      "salary": null,
      "workMode": null,
      "publishedAt": "Opublikowana: 19 marca 2026",
      "url": "https://www.pracuj.pl/praca/operator-ka-montazu-slusarz-wyry-pow-mikolowski-na-wierzysko-5,oferta,1004717016"
    },
    {
      "id": "1004707961",
      "title": "Analityk Biznesowo-Systemowy / Analityczka Biznesowo-Systemowa",
      "company": "FINTURE Sp. z o.o.",
      "location": "Warszawa",
      "salary": null,
      "workMode": null,
      "publishedAt": "Opublikowana: 19 marca 2026",
      "url": "https://www.pracuj.pl/praca/analityk-biznesowo-systemowy-analityczka-biznesowo-systemowa-warszawa,oferta,1004707961"
    },
    {
      "id": "11888093",
      "title": "Lifeguard",
      "company": "Good Time Group",
      "location": "Rhodes, Southern Aegean, Grecja",
      "salary": null,
      "workMode": null,
      "publishedAt": "Opublikowana: 19 marca 2026",
      "url": "https://www.pracuj.pl/praca/lifeguard-greece,oferta,11888093"
    },
    {
      "id": "1004704257",
      "title": "Listonosz / Listonoszka",
      "company": "Poczta Polska Spółka Akcyjna",
      "location": "Łęczna",
      "salary": null,
      "workMode": null,
      "publishedAt": "Opublikowana: 19 marca 2026",
      "url": "https://www.pracuj.pl/praca/listonosz-listonoszka-leczna-aleja-jana-pawla-ii-89,oferta,1004704257"
    },
    {
      "id": "1004693140",
      "title": "Monter instalacji klimatyzacji - chłodnictwa",
      "company": "ARSEM sp. z o.o.",
      "location": "Łódź",
      "salary": null,
      "workMode": null,
      "publishedAt": "Opublikowana: 19 marca 2026",
      "url": "https://www.pracuj.pl/praca/monter-instalacji-klimatyzacji-chlodnictwa-lodz,oferta,1004693140"
    },
    {
      "id": "1004693138",
      "title": "Specjalista / Specjalistka ds. zamówień publicznych",
      "company": "KANCELARIA RADCÓW PRAWNYCH ZYGMUNT JERZMANOWSKI I WSPÓLNICY sp.k.",
      "location": "Miejsce pracy:Cała Polska (praca zdalna)\nSiedziba firmy:Poznań, Jeżyce",
      "salary": null,
      "workMode": null,
      "publishedAt": "Opublikowana: 19 marca 2026",
      "url": "https://www.pracuj.pl/praca/specjalista-specjalistka-ds-zamowien-publicznych-poznan-mickiewicza-14,oferta,1004693138"
    },
    {
      "id": "1004693135",
      "title": "Diagnosta / Diagnostka stacji kontroli pojazdów",
      "company": "PRZEMYSŁOWY INSTYTUT MASZYN BUDOWLANYCH sp. z o.o.",
      "location": "Kobyłka",
      "salary": null,
      "workMode": null,
      "publishedAt": "Opublikowana: 19 marca 2026",
      "url": "https://www.pracuj.pl/praca/diagnosta-diagnostka-stacji-kontroli-pojazdow-kobylka-napoleona-2,oferta,1004693135"
    },
    {
      "id": "1004693132",
      "title": "Osoba na stanowisku inżyniera produktu",
      "company": "Thermod sp. z o.o.",
      "location": "Grodzisk Wielkopolski",
      "salary": null,
      "workMode": null,
      "publishedAt": "Opublikowana: 19 marca 2026",
      "url": "https://www.pracuj.pl/praca/osoba-na-stanowisku-inzyniera-produktu-grodzisk-wielkopolski,oferta,1004693132"
    },
    {
      "id": "1004683875",
      "title": "[Let's Orange] Praktyka w obszarze Finansów w Orange Polska",
      "company": "Orange Polska",
      "location": "Warszawa",
      "salary": null,
      "workMode": null,
      "publishedAt": "Opublikowana: 19 marca 2026",
      "url": "https://www.pracuj.pl/praca/let-s-orange-praktyka-w-obszarze-finansow-w-orange-polska-warszawa,oferta,1004683875"
    },
    {
      "id": "1004683873",
      "title": "[Let's Orange] Praktyka w obszarze Digital marketingu/UX/UI w Orange Polska",
      "company": "Orange Polska",
      "location": "Warszawa",
      "salary": null,
      "workMode": null,
      "publishedAt": "Opublikowana: 19 marca 2026",
      "url": "https://www.pracuj.pl/praca/let-s-orange-praktyka-w-obszarze-digital-marketingu-ux-ui-w-orange-polska-warszawa,oferta,1004683873"
    },
    {
      "id": "1004693149",
      "title": "Lider / Liderka Obszaru (Brygadzista / Brygadzistka)",
      "company": "SMP Poland Sp. z o.o.",
      "location": "Białystok, Nowe Miasto",
      "salary": null,
      "workMode": null,
      "publishedAt": "Opublikowana: 19 marca 2026",
      "url": "https://www.pracuj.pl/praca/lider-liderka-obszaru-brygadzista-brygadzistka-bialystok-magazynowa-2,oferta,1004693149"
    },
    {
      "id": "1004693130",
      "title": "Specjalista/Specjalistka ds. planowania i rozliczania inwestycji i remontów",
      "company": "MPK Sp. z o.o.",
      "location": "Wrocław, Krzyki",
      "salary": null,
      "workMode": null,
      "publishedAt": "Opublikowana: 19 marca 2026",
      "url": "https://www.pracuj.pl/praca/specjalista-specjalistka-ds-planowania-i-rozliczania-inwestycji-i-remontow-wroclaw-powstancow-slaskich-209,oferta,1004693130"
    },
    {
      "id": "1004717013",
      "title": "Starszy specjalista / Starsza specjalistka ds. kadr i płac",
      "company": "IRIDEX ROBOTICS sp. z o.o.",
      "location": "Sokołów (pow. pruszkowski)",
      "salary": null,
      "workMode": null,
      "publishedAt": "Opublikowana: 19 marca 2026",
      "url": "https://www.pracuj.pl/praca/starszy-specjalista-starsza-specjalistka-ds-kadr-i-plac-sokolow-pow-pruszkowski-sokolowska-45b,oferta,1004717013"
    },
    {
      "id": "1004717014",
      "title": "Samodzielny księgowy / Samodzielna księgowa",
      "company": "RMDK SPÓŁKA Z OGRANICZONĄ ODPOWIEDZIALNOŚCIĄ",
      "location": "Warszawa",
      "salary": null,
      "workMode": null,
      "publishedAt": "Opublikowana: 19 marca 2026",
      "url": "https://www.pracuj.pl/praca/samodzielny-ksiegowy-samodzielna-ksiegowa-warszawa,oferta,1004717014"
    },
    {
      "id": "1004717015",
      "title": "Operator lasera CNC",
      "company": "Bendsteel",
      "location": "Brzesko",
      "salary": null,
      "workMode": null,
      "publishedAt": "Opublikowana: 19 marca 2026",
      "url": "https://www.pracuj.pl/praca/operator-lasera-cnc-brzesko-jodlowska-1,oferta,1004717015"
    },
    {
      "id": "1004717011",
      "title": "Spedytor / Spedytorka (transport drogowy, lotniczy, morski i kolejowy)",
      "company": "HPL GROUP sp. z o.o.",
      "location": "Wrocław, Fabryczna",
      "salary": null,
      "workMode": null,
      "publishedAt": "Opublikowana: 19 marca 2026",
      "url": "https://www.pracuj.pl/praca/spedytor-spedytorka-transport-drogowy-lotniczy-morski-i-kolejowy-wroclaw-legnicka-59,oferta,1004717011"
    },
    {
      "id": "1004717012",
      "title": "Kelner / Kelnerka - Barman / Barmanka",
      "company": "Państwowy Zespół Ludowy Pieśni i Tańca \"Mazowsze\" im. T. Sygietyńskiego",
      "location": "Otrębusy (pow. pruszkowski)",
      "salary": null,
      "workMode": null,
      "publishedAt": "Opublikowana: 19 marca 2026",
      "url": "https://www.pracuj.pl/praca/kelner-kelnerka-barman-barmanka-otrebusy-pow-pruszkowski-swierkowa-2,oferta,1004717012"
    },
    {
      "id": "1004693125",
      "title": "Przedstawiciel Handlowy (Terenowy) – Usługi Sprzątające",
      "company": "MEGAMINI SPÓŁKA Z OGRANICZONĄ ODPOWIEDZIALNOŚCIĄ SPÓŁKA KOMANDYTOWA",
      "location": "Gdańsk",
      "salary": null,
      "workMode": null,
      "publishedAt": "Opublikowana: 19 marca 2026",
      "url": "https://www.pracuj.pl/praca/przedstawiciel-handlowy-terenowy-uslugi-sprzatajace-gdansk,oferta,1004693125"
    },
    {
      "id": "1004717009",
      "title": "Doradca / Doradczyni ds. techniczno-handlowych",
      "company": "LIFT PROFIL sp. z o.o. SPÓŁKA KOMANDYTOWA",
      "location": "Częstochowa, Zawodzie - Dąbie",
      "salary": null,
      "workMode": null,
      "publishedAt": "Opublikowana: 19 marca 2026",
      "url": "https://www.pracuj.pl/praca/doradca-doradczyni-ds-techniczno-handlowych-czestochowa-zaciszna-12,oferta,1004717009"
    },
    {
      "id": "1004717010",
      "title": "Specjalista / Specjalistka ds. kadr i płac",
      "company": "REVERSE BUSINESS SUPPORT sp. z o.o.",
      "location": "Warszawa, Ochota",
      "salary": null,
      "workMode": null,
      "publishedAt": "Opublikowana: 19 marca 2026",
      "url": "https://www.pracuj.pl/praca/specjalista-specjalistka-ds-kadr-i-plac-warszawa-raszynska-48,oferta,1004717010"
    },
    {
      "id": "1004693113",
      "title": "Terapeuta / Terapeutka integracji sensorycznej",
      "company": "Fundacja Bluebees / Punkt Przedszkolny Bluebees - Akademia dla Dzieci z Autyzmem",
      "location": "Warszawa, Bielany",
      "salary": null,
      "workMode": null,
      "publishedAt": "Opublikowana: 19 marca 2026",
      "url": "https://www.pracuj.pl/praca/terapeuta-terapeutka-integracji-sensorycznej-warszawa-anny-jagiellonki-2a,oferta,1004693113"
    },
    {
      "id": "1004717007",
      "title": "Księgowy / Księgowa",
      "company": "DALMOR Property Management Sp. z o.o.",
      "location": "Gdynia, Śródmieście",
      "salary": null,
      "workMode": null,
      "publishedAt": "Opublikowana: 19 marca 2026",
      "url": "https://www.pracuj.pl/praca/ksiegowy-ksiegowa-gdynia-antoniego-hryniewickiego-10,oferta,1004717007"
    },
    {
      "id": "1004717008",
      "title": "Młodszy/a Specjalista/ka ds. Kancelaryjno-Organizacyjnych",
      "company": "MUZEUM NARODOWE W SZCZECINIE",
      "location": "Szczecin",
      "salary": null,
      "workMode": null,
      "publishedAt": "Opublikowana: 19 marca 2026",
      "url": "https://www.pracuj.pl/praca/mlodszy-a-specjalista-ka-ds-kancelaryjno-organizacyjnych-szczecin,oferta,1004717008"
    },
    {
      "id": "1004701514",
      "title": "Księgowy / Księgowa",
      "company": "MUNIAK sp. z o.o. SPÓŁKA KOMANDYTOWA",
      "location": "Warszawa, Bemowo",
      "salary": null,
      "workMode": null,
      "publishedAt": "Opublikowana: 19 marca 2026",
      "url": "https://www.pracuj.pl/praca/ksiegowy-ksiegowa-warszawa-dywizjonu-303-139,oferta,1004701514"
    },
    {
      "id": "1004717006",
      "title": "Asystent / Asystentka zarządu",
      "company": "IFDS DOM MAKLERSKI S.A.",
      "location": "Warszawa, Mokotów",
      "salary": null,
      "workMode": null,
      "publishedAt": "Opublikowana: 19 marca 2026",
      "url": "https://www.pracuj.pl/praca/asystent-asystentka-zarzadu-warszawa-konstruktorska-12,oferta,1004717006"
    },
    {
      "id": "1004717005",
      "title": "Rejestrator medyczny / Rejestratorka medyczna",
      "company": "CENTRUM STOMATOLOGII CANDEO DENTAL CLINIC WIESŁAW HĘDZELEK sp.k.",
      "location": "Poznań",
      "salary": null,
      "workMode": null,
      "publishedAt": "Opublikowana: 19 marca 2026",
      "url": "https://www.pracuj.pl/praca/rejestrator-medyczny-rejestratorka-medyczna-poznan,oferta,1004717005"
    }
  ]
}